ghpeek/__init__.py
ghpeek/__main__.py
ghpeek/app.py
ghpeek/state.py
ghpeek-0.2.0.dist-info/licenses/LICENSE
ghpeek-0.2.0.dist-info/METADATA
ghpeek-0.2.0.dist-info/WHEEL
ghpeek-0.2.0.dist-info/entry_points.txt
ghpeek-0.2.0.dist-info/top_level.txt
ghpeek-0.2.0.dist-info/RECORD
