Metadata-Version: 2.4
Name: ghpeek
Version: 0.2.0
Summary: Stylish TUI to browse GitHub repositories, issues, and pull requests.
Requires-Python: >=3.10
License-File: LICENSE
Requires-Dist: textual
Requires-Dist: PyGithub
Requires-Dist: rich
Requires-Dist: markdown
Requires-Dist: python-dotenv
Dynamic: license-file
